[
  {
    "exchange": "OKEx",
    "pair": "NEO_USD",
    "rawPair": "NEO-USD-SWAP",
    "fundingRate": 0.00158996,
    "fundingTime": 1597507200000,
    "fundingTimeStr": "2020-08-15T16:00:00.000Z"
  },
  {
    "exchange": "OKEx",
    "pair": "NEO_USD",
    "rawPair": "NEO-USD-SWAP",
    "fundingRate": 0.00075891,
    "fundingTime": 1597536000000,
    "fundingTimeStr": "2020-08-16T00:00:00.000Z"
  },
  {
    "exchange": "OKEx",
    "pair": "NEO_USD",
    "rawPair": "NEO-USD-SWAP",
    "fundingRate": 0.00155451,
    "fundingTime": 1597564800000,
    "fundingTimeStr": "2020-08-16T08:00:00.000Z"
  },
  {
    "exchange": "OKEx",
    "pair": "NEO_USD",
    "rawPair": "NEO-USD-SWAP",
    "fundingRate": 0.00043392,
    "fundingTime": 1597593600000,
    "fundingTimeStr": "2020-08-16T16:00:00.000Z"
  },
  {
    "exchange": "OKEx",
    "pair": "NEO_USD",
    "rawPair": "NEO-USD-SWAP",
    "fundingRate": 0.00150579,
    "fundingTime": 1597622400000,
    "fundingTimeStr": "2020-08-17T00:00:00.000Z"
  },
  {
    "exchange": "OKEx",
    "pair": "NEO_USD",
    "rawPair": "NEO-USD-SWAP",
    "fundingRate": 0.00090019,
    "fundingTime": 1597651200000,
    "fundingTimeStr": "2020-08-17T08:00:00.000Z"
  },
  {
    "exchange": "OKEx",
    "pair": "NEO_USD",
    "rawPair": "NEO-USD-SWAP",
    "fundingRate": 0.00136453,
    "fundingTime": 1597680000000,
    "fundingTimeStr": "2020-08-17T16:00:00.000Z"
  },
  {
    "exchange": "OKEx",
    "pair": "NEO_USD",
    "rawPair": "NEO-USD-SWAP",
    "fundingRate": 0.00045021,
    "fundingTime": 1597708800000,
    "fundingTimeStr": "2020-08-18T00:00:00.000Z"
  },
  {
    "exchange": "OKEx",
    "pair": "NEO_USD",
    "rawPair": "NEO-USD-SWAP",
    "fundingRate": 0.0012886,
    "fundingTime": 1597737600000,
    "fundingTimeStr": "2020-08-18T08:00:00.000Z"
  },
  {
    "exchange": "OKEx",
    "pair": "NEO_USD",
    "rawPair": "NEO-USD-SWAP",
    "fundingRate": 0.00009094,
    "fundingTime": 1597766400000,
    "fundingTimeStr": "2020-08-18T16:00:00.000Z"
  },
  {
    "exchange": "OKEx",
    "pair": "NEO_USD",
    "rawPair": "NEO-USD-SWAP",
    "fundingRate": 0.00032672,
    "fundingTime": 1597795200000,
    "fundingTimeStr": "2020-08-19T00:00:00.000Z"
  },
  {
    "exchange": "OKEx",
    "pair": "NEO_USD",
    "rawPair": "NEO-USD-SWAP",
    "fundingRate": 0.00003605,
    "fundingTime": 1597824000000,
    "fundingTimeStr": "2020-08-19T08:00:00.000Z"
  },
  {
    "exchange": "OKEx",
    "pair": "NEO_USD",
    "rawPair": "NEO-USD-SWAP",
    "fundingRate": 0.00025664,
    "fundingTime": 1597852800000,
    "fundingTimeStr": "2020-08-19T16:00:00.000Z"
  },
  {
    "exchange": "OKEx",
    "pair": "NEO_USD",
    "rawPair": "NEO-USD-SWAP",
    "fundingRate": 0.00045631,
    "fundingTime": 1597881600000,
    "fundingTimeStr": "2020-08-20T00:00:00.000Z"
  },
  {
    "exchange": "OKEx",
    "pair": "NEO_USD",
    "rawPair": "NEO-USD-SWAP",
    "fundingRate": -0.00002628,
    "fundingTime": 1597910400000,
    "fundingTimeStr": "2020-08-20T08:00:00.000Z"
  },
  {
    "exchange": "OKEx",
    "pair": "NEO_USD",
    "rawPair": "NEO-USD-SWAP",
    "fundingRate": 0.00034511,
    "fundingTime": 1597939200000,
    "fundingTimeStr": "2020-08-20T16:00:00.000Z"
  },
  {
    "exchange": "OKEx",
    "pair": "NEO_USD",
    "rawPair": "NEO-USD-SWAP",
    "fundingRate": 0.0004772,
    "fundingTime": 1597968000000,
    "fundingTimeStr": "2020-08-21T00:00:00.000Z"
  },
  {
    "exchange": "OKEx",
    "pair": "NEO_USD",
    "rawPair": "NEO-USD-SWAP",
    "fundingRate": 0.00009331,
    "fundingTime": 1597996800000,
    "fundingTimeStr": "2020-08-21T08:00:00.000Z"
  },
  {
    "exchange": "OKEx",
    "pair": "NEO_USD",
    "rawPair": "NEO-USD-SWAP",
    "fundingRate": 0.0011719,
    "fundingTime": 1598025600000,
    "fundingTimeStr": "2020-08-21T16:00:00.000Z"
  },
  {
    "exchange": "OKEx",
    "pair": "NEO_USD",
    "rawPair": "NEO-USD-SWAP",
    "fundingRate": 0.00018562,
    "fundingTime": 1598054400000,
    "fundingTimeStr": "2020-08-22T00:00:00.000Z"
  },
  {
    "exchange": "OKEx",
    "pair": "NEO_USD",
    "rawPair": "NEO-USD-SWAP",
    "fundingRate": -0.00006514,
    "fundingTime": 1598083200000,
    "fundingTimeStr": "2020-08-22T08:00:00.000Z"
  },
  {
    "exchange": "OKEx",
    "pair": "NEO_USD",
    "rawPair": "NEO-USD-SWAP",
    "fundingRate": -0.00049154,
    "fundingTime": 1598112000000,
    "fundingTimeStr": "2020-08-22T16:00:00.000Z"
  },
  {
    "exchange": "OKEx",
    "pair": "NEO_USD",
    "rawPair": "NEO-USD-SWAP",
    "fundingRate": 0.00002818,
    "fundingTime": 1598140800000,
    "fundingTimeStr": "2020-08-23T00:00:00.000Z"
  },
  {
    "exchange": "OKEx",
    "pair": "NEO_USD",
    "rawPair": "NEO-USD-SWAP",
    "fundingRate": 0.00033559,
    "fundingTime": 1598169600000,
    "fundingTimeStr": "2020-08-23T08:00:00.000Z"
  },
  {
    "exchange": "OKEx",
    "pair": "NEO_USD",
    "rawPair": "NEO-USD-SWAP",
    "fundingRate": -0.0001202,
    "fundingTime": 1598198400000,
    "fundingTimeStr": "2020-08-23T16:00:00.000Z"
  },
  {
    "exchange": "OKEx",
    "pair": "NEO_USD",
    "rawPair": "NEO-USD-SWAP",
    "fundingRate": -0.00003483,
    "fundingTime": 1598227200000,
    "fundingTimeStr": "2020-08-24T00:00:00.000Z"
  },
  {
    "exchange": "OKEx",
    "pair": "NEO_USD",
    "rawPair": "NEO-USD-SWAP",
    "fundingRate": 0.00068893,
    "fundingTime": 1598256000000,
    "fundingTimeStr": "2020-08-24T08:00:00.000Z"
  },
  {
    "exchange": "OKEx",
    "pair": "NEO_USD",
    "rawPair": "NEO-USD-SWAP",
    "fundingRate": 0.00054558,
    "fundingTime": 1598284800000,
    "fundingTimeStr": "2020-08-24T16:00:00.000Z"
  },
  {
    "exchange": "OKEx",
    "pair": "NEO_USD",
    "rawPair": "NEO-USD-SWAP",
    "fundingRate": 0.00008998,
    "fundingTime": 1598313600000,
    "fundingTimeStr": "2020-08-25T00:00:00.000Z"
  },
  {
    "exchange": "OKEx",
    "pair": "NEO_USD",
    "rawPair": "NEO-USD-SWAP",
    "fundingRate": 0.00091319,
    "fundingTime": 1598342400000,
    "fundingTimeStr": "2020-08-25T08:00:00.000Z"
  },
  {
    "exchange": "OKEx",
    "pair": "NEO_USD",
    "rawPair": "NEO-USD-SWAP",
    "fundingRate": -0.00062741,
    "fundingTime": 1598371200000,
    "fundingTimeStr": "2020-08-25T16:00:00.000Z"
  },
  {
    "exchange": "OKEx",
    "pair": "NEO_USD",
    "rawPair": "NEO-USD-SWAP",
    "fundingRate": 0.00050137,
    "fundingTime": 1598400000000,
    "fundingTimeStr": "2020-08-26T00:00:00.000Z"
  },
  {
    "exchange": "OKEx",
    "pair": "NEO_USD",
    "rawPair": "NEO-USD-SWAP",
    "fundingRate": -0.00096603,
    "fundingTime": 1598428800000,
    "fundingTimeStr": "2020-08-26T08:00:00.000Z"
  },
  {
    "exchange": "OKEx",
    "pair": "NEO_USD",
    "rawPair": "NEO-USD-SWAP",
    "fundingRate": 0.00035258,
    "fundingTime": 1598457600000,
    "fundingTimeStr": "2020-08-26T16:00:00.000Z"
  },
  {
    "exchange": "OKEx",
    "pair": "NEO_USD",
    "rawPair": "NEO-USD-SWAP",
    "fundingRate": -0.00062926,
    "fundingTime": 1598486400000,
    "fundingTimeStr": "2020-08-27T00:00:00.000Z"
  },
  {
    "exchange": "OKEx",
    "pair": "NEO_USD",
    "rawPair": "NEO-USD-SWAP",
    "fundingRate": 0.00014096,
    "fundingTime": 1598515200000,
    "fundingTimeStr": "2020-08-27T08:00:00.000Z"
  },
  {
    "exchange": "OKEx",
    "pair": "NEO_USD",
    "rawPair": "NEO-USD-SWAP",
    "fundingRate": 0.00024425,
    "fundingTime": 1598544000000,
    "fundingTimeStr": "2020-08-27T16:00:00.000Z"
  },
  {
    "exchange": "OKEx",
    "pair": "NEO_USD",
    "rawPair": "NEO-USD-SWAP",
    "fundingRate": 0.00071154,
    "fundingTime": 1598572800000,
    "fundingTimeStr": "2020-08-28T00:00:00.000Z"
  },
  {
    "exchange": "OKEx",
    "pair": "NEO_USD",
    "rawPair": "NEO-USD-SWAP",
    "fundingRate": -0.00088287,
    "fundingTime": 1598601600000,
    "fundingTimeStr": "2020-08-28T08:00:00.000Z"
  },
  {
    "exchange": "OKEx",
    "pair": "NEO_USD",
    "rawPair": "NEO-USD-SWAP",
    "fundingRate": 0.00075668,
    "fundingTime": 1598630400000,
    "fundingTimeStr": "2020-08-28T16:00:00.000Z"
  },
  {
    "exchange": "OKEx",
    "pair": "NEO_USD",
    "rawPair": "NEO-USD-SWAP",
    "fundingRate": 0.00010914,
    "fundingTime": 1598659200000,
    "fundingTimeStr": "2020-08-29T00:00:00.000Z"
  },
  {
    "exchange": "OKEx",
    "pair": "NEO_USD",
    "rawPair": "NEO-USD-SWAP",
    "fundingRate": 0.00055309,
    "fundingTime": 1598688000000,
    "fundingTimeStr": "2020-08-29T08:00:00.000Z"
  },
  {
    "exchange": "OKEx",
    "pair": "NEO_USD",
    "rawPair": "NEO-USD-SWAP",
    "fundingRate": -0.0000336,
    "fundingTime": 1598716800000,
    "fundingTimeStr": "2020-08-29T16:00:00.000Z"
  },
  {
    "exchange": "OKEx",
    "pair": "NEO_USD",
    "rawPair": "NEO-USD-SWAP",
    "fundingRate": 0.0004292,
    "fundingTime": 1598745600000,
    "fundingTimeStr": "2020-08-30T00:00:00.000Z"
  },
  {
    "exchange": "OKEx",
    "pair": "NEO_USD",
    "rawPair": "NEO-USD-SWAP",
    "fundingRate": 0.00097953,
    "fundingTime": 1598774400000,
    "fundingTimeStr": "2020-08-30T08:00:00.000Z"
  },
  {
    "exchange": "OKEx",
    "pair": "NEO_USD",
    "rawPair": "NEO-USD-SWAP",
    "fundingRate": 0.00015644,
    "fundingTime": 1598803200000,
    "fundingTimeStr": "2020-08-30T16:00:00.000Z"
  },
  {
    "exchange": "OKEx",
    "pair": "NEO_USD",
    "rawPair": "NEO-USD-SWAP",
    "fundingRate": 0.00114809,
    "fundingTime": 1598832000000,
    "fundingTimeStr": "2020-08-31T00:00:00.000Z"
  },
  {
    "exchange": "OKEx",
    "pair": "NEO_USD",
    "rawPair": "NEO-USD-SWAP",
    "fundingRate": 0.00007168,
    "fundingTime": 1598860800000,
    "fundingTimeStr": "2020-08-31T08:00:00.000Z"
  },
  {
    "exchange": "OKEx",
    "pair": "NEO_USD",
    "rawPair": "NEO-USD-SWAP",
    "fundingRate": 0.001028,
    "fundingTime": 1598889600000,
    "fundingTimeStr": "2020-08-31T16:00:00.000Z"
  },
  {
    "exchange": "OKEx",
    "pair": "NEO_USD",
    "rawPair": "NEO-USD-SWAP",
    "fundingRate": 0.00019268,
    "fundingTime": 1598918400000,
    "fundingTimeStr": "2020-09-01T00:00:00.000Z"
  },
  {
    "exchange": "OKEx",
    "pair": "NEO_USD",
    "rawPair": "NEO-USD-SWAP",
    "fundingRate": 0.00100885,
    "fundingTime": 1598947200000,
    "fundingTimeStr": "2020-09-01T08:00:00.000Z"
  },
  {
    "exchange": "OKEx",
    "pair": "NEO_USD",
    "rawPair": "NEO-USD-SWAP",
    "fundingRate": 0.00090986,
    "fundingTime": 1598976000000,
    "fundingTimeStr": "2020-09-01T16:00:00.000Z"
  },
  {
    "exchange": "OKEx",
    "pair": "NEO_USD",
    "rawPair": "NEO-USD-SWAP",
    "fundingRate": 0.00124538,
    "fundingTime": 1599004800000,
    "fundingTimeStr": "2020-09-02T00:00:00.000Z"
  },
  {
    "exchange": "OKEx",
    "pair": "NEO_USD",
    "rawPair": "NEO-USD-SWAP",
    "fundingRate": 0.00132278,
    "fundingTime": 1599033600000,
    "fundingTimeStr": "2020-09-02T08:00:00.000Z"
  },
  {
    "exchange": "OKEx",
    "pair": "NEO_USD",
    "rawPair": "NEO-USD-SWAP",
    "fundingRate": 0.00067226,
    "fundingTime": 1599062400000,
    "fundingTimeStr": "2020-09-02T16:00:00.000Z"
  },
  {
    "exchange": "OKEx",
    "pair": "NEO_USD",
    "rawPair": "NEO-USD-SWAP",
    "fundingRate": 0.00082348,
    "fundingTime": 1599091200000,
    "fundingTimeStr": "2020-09-03T00:00:00.000Z"
  },
  {
    "exchange": "OKEx",
    "pair": "NEO_USD",
    "rawPair": "NEO-USD-SWAP",
    "fundingRate": -0.00022803,
    "fundingTime": 1599120000000,
    "fundingTimeStr": "2020-09-03T08:00:00.000Z"
  },
  {
    "exchange": "OKEx",
    "pair": "NEO_USD",
    "rawPair": "NEO-USD-SWAP",
    "fundingRate": 0.00093575,
    "fundingTime": 1599148800000,
    "fundingTimeStr": "2020-09-03T16:00:00.000Z"
  },
  {
    "exchange": "OKEx",
    "pair": "NEO_USD",
    "rawPair": "NEO-USD-SWAP",
    "fundingRate": 0.00046,
    "fundingTime": 1599177600000,
    "fundingTimeStr": "2020-09-04T00:00:00.000Z"
  },
  {
    "exchange": "OKEx",
    "pair": "NEO_USD",
    "rawPair": "NEO-USD-SWAP",
    "fundingRate": -0.00028589,
    "fundingTime": 1599206400000,
    "fundingTimeStr": "2020-09-04T08:00:00.000Z"
  },
  {
    "exchange": "OKEx",
    "pair": "NEO_USD",
    "rawPair": "NEO-USD-SWAP",
    "fundingRate": -0.00089651,
    "fundingTime": 1599235200000,
    "fundingTimeStr": "2020-09-04T16:00:00.000Z"
  },
  {
    "exchange": "OKEx",
    "pair": "NEO_USD",
    "rawPair": "NEO-USD-SWAP",
    "fundingRate": -0.00004284,
    "fundingTime": 1599264000000,
    "fundingTimeStr": "2020-09-05T00:00:00.000Z"
  },
  {
    "exchange": "OKEx",
    "pair": "NEO_USD",
    "rawPair": "NEO-USD-SWAP",
    "fundingRate": -0.00168636,
    "fundingTime": 1599292800000,
    "fundingTimeStr": "2020-09-05T08:00:00.000Z"
  },
  {
    "exchange": "OKEx",
    "pair": "NEO_USD",
    "rawPair": "NEO-USD-SWAP",
    "fundingRate": -0.00011027,
    "fundingTime": 1599321600000,
    "fundingTimeStr": "2020-09-05T16:00:00.000Z"
  },
  {
    "exchange": "OKEx",
    "pair": "NEO_USD",
    "rawPair": "NEO-USD-SWAP",
    "fundingRate": -0.00124219,
    "fundingTime": 1599350400000,
    "fundingTimeStr": "2020-09-06T00:00:00.000Z"
  },
  {
    "exchange": "OKEx",
    "pair": "NEO_USD",
    "rawPair": "NEO-USD-SWAP",
    "fundingRate": -0.00155211,
    "fundingTime": 1599379200000,
    "fundingTimeStr": "2020-09-06T08:00:00.000Z"
  },
  {
    "exchange": "OKEx",
    "pair": "NEO_USD",
    "rawPair": "NEO-USD-SWAP",
    "fundingRate": -0.00043072,
    "fundingTime": 1599408000000,
    "fundingTimeStr": "2020-09-06T16:00:00.000Z"
  },
  {
    "exchange": "OKEx",
    "pair": "NEO_USD",
    "rawPair": "NEO-USD-SWAP",
    "fundingRate": -0.00023694,
    "fundingTime": 1599436800000,
    "fundingTimeStr": "2020-09-07T00:00:00.000Z"
  },
  {
    "exchange": "OKEx",
    "pair": "NEO_USD",
    "rawPair": "NEO-USD-SWAP",
    "fundingRate": -0.00073317,
    "fundingTime": 1599465600000,
    "fundingTimeStr": "2020-09-07T08:00:00.000Z"
  },
  {
    "exchange": "OKEx",
    "pair": "NEO_USD",
    "rawPair": "NEO-USD-SWAP",
    "fundingRate": -0.00001661,
    "fundingTime": 1599494400000,
    "fundingTimeStr": "2020-09-07T16:00:00.000Z"
  },
  {
    "exchange": "OKEx",
    "pair": "NEO_USD",
    "rawPair": "NEO-USD-SWAP",
    "fundingRate": -0.00062227,
    "fundingTime": 1599523200000,
    "fundingTimeStr": "2020-09-08T00:00:00.000Z"
  },
  {
    "exchange": "OKEx",
    "pair": "NEO_USD",
    "rawPair": "NEO-USD-SWAP",
    "fundingRate": -0.00077193,
    "fundingTime": 1599552000000,
    "fundingTimeStr": "2020-09-08T08:00:00.000Z"
  },
  {
    "exchange": "OKEx",
    "pair": "NEO_USD",
    "rawPair": "NEO-USD-SWAP",
    "fundingRate": -0.00044428,
    "fundingTime": 1599580800000,
    "fundingTimeStr": "2020-09-08T16:00:00.000Z"
  },
  {
    "exchange": "OKEx",
    "pair": "NEO_USD",
    "rawPair": "NEO-USD-SWAP",
    "fundingRate": -0.00058083,
    "fundingTime": 1599609600000,
    "fundingTimeStr": "2020-09-09T00:00:00.000Z"
  },
  {
    "exchange": "OKEx",
    "pair": "NEO_USD",
    "rawPair": "NEO-USD-SWAP",
    "fundingRate": -0.0001761,
    "fundingTime": 1599638400000,
    "fundingTimeStr": "2020-09-09T08:00:00.000Z"
  },
  {
    "exchange": "OKEx",
    "pair": "NEO_USD",
    "rawPair": "NEO-USD-SWAP",
    "fundingRate": -0.00035928,
    "fundingTime": 1599667200000,
    "fundingTimeStr": "2020-09-09T16:00:00.000Z"
  },
  {
    "exchange": "OKEx",
    "pair": "NEO_USD",
    "rawPair": "NEO-USD-SWAP",
    "fundingRate": -0.00039269,
    "fundingTime": 1599696000000,
    "fundingTimeStr": "2020-09-10T00:00:00.000Z"
  },
  {
    "exchange": "OKEx",
    "pair": "NEO_USD",
    "rawPair": "NEO-USD-SWAP",
    "fundingRate": -0.00098401,
    "fundingTime": 1599724800000,
    "fundingTimeStr": "2020-09-10T08:00:00.000Z"
  },
  {
    "exchange": "OKEx",
    "pair": "NEO_USD",
    "rawPair": "NEO-USD-SWAP",
    "fundingRate": 0.00047726,
    "fundingTime": 1599753600000,
    "fundingTimeStr": "2020-09-10T16:00:00.000Z"
  },
  {
    "exchange": "OKEx",
    "pair": "NEO_USD",
    "rawPair": "NEO-USD-SWAP",
    "fundingRate": -0.00182213,
    "fundingTime": 1599782400000,
    "fundingTimeStr": "2020-09-11T00:00:00.000Z"
  },
  {
    "exchange": "OKEx",
    "pair": "NEO_USD",
    "rawPair": "NEO-USD-SWAP",
    "fundingRate": -0.00003377,
    "fundingTime": 1599811200000,
    "fundingTimeStr": "2020-09-11T08:00:00.000Z"
  },
  {
    "exchange": "OKEx",
    "pair": "NEO_USD",
    "rawPair": "NEO-USD-SWAP",
    "fundingRate": -0.00059253,
    "fundingTime": 1599840000000,
    "fundingTimeStr": "2020-09-11T16:00:00.000Z"
  },
  {
    "exchange": "OKEx",
    "pair": "NEO_USD",
    "rawPair": "NEO-USD-SWAP",
    "fundingRate": 0.00055454,
    "fundingTime": 1599868800000,
    "fundingTimeStr": "2020-09-12T00:00:00.000Z"
  },
  {
    "exchange": "OKEx",
    "pair": "NEO_USD",
    "rawPair": "NEO-USD-SWAP",
    "fundingRate": -0.00063488,
    "fundingTime": 1599897600000,
    "fundingTimeStr": "2020-09-12T08:00:00.000Z"
  },
  {
    "exchange": "OKEx",
    "pair": "NEO_USD",
    "rawPair": "NEO-USD-SWAP",
    "fundingRate": 0.0001132,
    "fundingTime": 1599926400000,
    "fundingTimeStr": "2020-09-12T16:00:00.000Z"
  },
  {
    "exchange": "OKEx",
    "pair": "NEO_USD",
    "rawPair": "NEO-USD-SWAP",
    "fundingRate": -0.00047411,
    "fundingTime": 1599955200000,
    "fundingTimeStr": "2020-09-13T00:00:00.000Z"
  },
  {
    "exchange": "OKEx",
    "pair": "NEO_USD",
    "rawPair": "NEO-USD-SWAP",
    "fundingRate": 0.00046249,
    "fundingTime": 1599984000000,
    "fundingTimeStr": "2020-09-13T08:00:00.000Z"
  },
  {
    "exchange": "OKEx",
    "pair": "NEO_USD",
    "rawPair": "NEO-USD-SWAP",
    "fundingRate": -0.00035678,
    "fundingTime": 1600012800000,
    "fundingTimeStr": "2020-09-13T16:00:00.000Z"
  },
  {
    "exchange": "OKEx",
    "pair": "NEO_USD",
    "rawPair": "NEO-USD-SWAP",
    "fundingRate": 0.00051814,
    "fundingTime": 1600041600000,
    "fundingTimeStr": "2020-09-14T00:00:00.000Z"
  },
  {
    "exchange": "OKEx",
    "pair": "NEO_USD",
    "rawPair": "NEO-USD-SWAP",
    "fundingRate": -0.00039076,
    "fundingTime": 1600070400000,
    "fundingTimeStr": "2020-09-14T08:00:00.000Z"
  },
  {
    "exchange": "OKEx",
    "pair": "NEO_USD",
    "rawPair": "NEO-USD-SWAP",
    "fundingRate": 0.00083989,
    "fundingTime": 1600099200000,
    "fundingTimeStr": "2020-09-14T16:00:00.000Z"
  },
  {
    "exchange": "OKEx",
    "pair": "NEO_USD",
    "rawPair": "NEO-USD-SWAP",
    "fundingRate": -0.00049085,
    "fundingTime": 1600128000000,
    "fundingTimeStr": "2020-09-15T00:00:00.000Z"
  },
  {
    "exchange": "OKEx",
    "pair": "NEO_USD",
    "rawPair": "NEO-USD-SWAP",
    "fundingRate": 0.00108698,
    "fundingTime": 1600156800000,
    "fundingTimeStr": "2020-09-15T08:00:00.000Z"
  },
  {
    "exchange": "OKEx",
    "pair": "NEO_USD",
    "rawPair": "NEO-USD-SWAP",
    "fundingRate": -0.00101898,
    "fundingTime": 1600185600000,
    "fundingTimeStr": "2020-09-15T16:00:00.000Z"
  },
  {
    "exchange": "OKEx",
    "pair": "NEO_USD",
    "rawPair": "NEO-USD-SWAP",
    "fundingRate": 0.00031008,
    "fundingTime": 1600214400000,
    "fundingTimeStr": "2020-09-16T00:00:00.000Z"
  },
  {
    "exchange": "OKEx",
    "pair": "NEO_USD",
    "rawPair": "NEO-USD-SWAP",
    "fundingRate": -0.00075654,
    "fundingTime": 1600243200000,
    "fundingTimeStr": "2020-09-16T08:00:00.000Z"
  },
  {
    "exchange": "OKEx",
    "pair": "NEO_USD",
    "rawPair": "NEO-USD-SWAP",
    "fundingRate": -0.00039239,
    "fundingTime": 1600272000000,
    "fundingTimeStr": "2020-09-16T16:00:00.000Z"
  },
  {
    "exchange": "OKEx",
    "pair": "NEO_USD",
    "rawPair": "NEO-USD-SWAP",
    "fundingRate": -0.00024612,
    "fundingTime": 1600300800000,
    "fundingTimeStr": "2020-09-17T00:00:00.000Z"
  },
  {
    "exchange": "OKEx",
    "pair": "NEO_USD",
    "rawPair": "NEO-USD-SWAP",
    "fundingRate": -0.00008364,
    "fundingTime": 1600329600000,
    "fundingTimeStr": "2020-09-17T08:00:00.000Z"
  },
  {
    "exchange": "OKEx",
    "pair": "NEO_USD",
    "rawPair": "NEO-USD-SWAP",
    "fundingRate": 0.0007489,
    "fundingTime": 1600358400000,
    "fundingTimeStr": "2020-09-17T16:00:00.000Z"
  },
  {
    "exchange": "OKEx",
    "pair": "NEO_USD",
    "rawPair": "NEO-USD-SWAP",
    "fundingRate": 0.00100147,
    "fundingTime": 1600387200000,
    "fundingTimeStr": "2020-09-18T00:00:00.000Z"
  },
  {
    "exchange": "OKEx",
    "pair": "NEO_USD",
    "rawPair": "NEO-USD-SWAP",
    "fundingRate": 0.00172236,
    "fundingTime": 1600416000000,
    "fundingTimeStr": "2020-09-18T08:00:00.000Z"
  },
  {
    "exchange": "OKEx",
    "pair": "NEO_USD",
    "rawPair": "NEO-USD-SWAP",
    "fundingRate": 0.00169201,
    "fundingTime": 1600444800000,
    "fundingTimeStr": "2020-09-18T16:00:00.000Z"
  },
  {
    "exchange": "OKEx",
    "pair": "NEO_USD",
    "rawPair": "NEO-USD-SWAP",
    "fundingRate": -0.00204883,
    "fundingTime": 1600473600000,
    "fundingTimeStr": "2020-09-19T00:00:00.000Z"
  },
  {
    "exchange": "OKEx",
    "pair": "NEO_USD",
    "rawPair": "NEO-USD-SWAP",
    "fundingRate": -0.00116871,
    "fundingTime": 1600502400000,
    "fundingTimeStr": "2020-09-19T08:00:00.000Z"
  },
  {
    "exchange": "OKEx",
    "pair": "NEO_USD",
    "rawPair": "NEO-USD-SWAP",
    "fundingRate": -0.00194809,
    "fundingTime": 1600531200000,
    "fundingTimeStr": "2020-09-19T16:00:00.000Z"
  },
  {
    "exchange": "OKEx",
    "pair": "NEO_USD",
    "rawPair": "NEO-USD-SWAP",
    "fundingRate": -0.00065769,
    "fundingTime": 1600560000000,
    "fundingTimeStr": "2020-09-20T00:00:00.000Z"
  },
  {
    "exchange": "OKEx",
    "pair": "NEO_USD",
    "rawPair": "NEO-USD-SWAP",
    "fundingRate": -0.00206752,
    "fundingTime": 1600588800000,
    "fundingTimeStr": "2020-09-20T08:00:00.000Z"
  },
  {
    "exchange": "OKEx",
    "pair": "NEO_USD",
    "rawPair": "NEO-USD-SWAP",
    "fundingRate": -0.00103166,
    "fundingTime": 1600617600000,
    "fundingTimeStr": "2020-09-20T16:00:00.000Z"
  },
  {
    "exchange": "OKEx",
    "pair": "NEO_USD",
    "rawPair": "NEO-USD-SWAP",
    "fundingRate": 0.00057275,
    "fundingTime": 1600646400000,
    "fundingTimeStr": "2020-09-21T00:00:00.000Z"
  },
  {
    "exchange": "OKEx",
    "pair": "NEO_USD",
    "rawPair": "NEO-USD-SWAP",
    "fundingRate": -0.00030006,
    "fundingTime": 1600675200000,
    "fundingTimeStr": "2020-09-21T08:00:00.000Z"
  },
  {
    "exchange": "OKEx",
    "pair": "NEO_USD",
    "rawPair": "NEO-USD-SWAP",
    "fundingRate": 0.00232322,
    "fundingTime": 1600704000000,
    "fundingTimeStr": "2020-09-21T16:00:00.000Z"
  },
  {
    "exchange": "OKEx",
    "pair": "NEO_USD",
    "rawPair": "NEO-USD-SWAP",
    "fundingRate": -0.00173822,
    "fundingTime": 1600732800000,
    "fundingTimeStr": "2020-09-22T00:00:00.000Z"
  },
  {
    "exchange": "OKEx",
    "pair": "NEO_USD",
    "rawPair": "NEO-USD-SWAP",
    "fundingRate": 0.00086684,
    "fundingTime": 1600761600000,
    "fundingTimeStr": "2020-09-22T08:00:00.000Z"
  },
  {
    "exchange": "OKEx",
    "pair": "NEO_USD",
    "rawPair": "NEO-USD-SWAP",
    "fundingRate": -0.00248986,
    "fundingTime": 1600790400000,
    "fundingTimeStr": "2020-09-22T16:00:00.000Z"
  },
  {
    "exchange": "OKEx",
    "pair": "NEO_USD",
    "rawPair": "NEO-USD-SWAP",
    "fundingRate": -0.00057253,
    "fundingTime": 1600819200000,
    "fundingTimeStr": "2020-09-23T00:00:00.000Z"
  },
  {
    "exchange": "OKEx",
    "pair": "NEO_USD",
    "rawPair": "NEO-USD-SWAP",
    "fundingRate": -0.00239049,
    "fundingTime": 1600848000000,
    "fundingTimeStr": "2020-09-23T08:00:00.000Z"
  },
  {
    "exchange": "OKEx",
    "pair": "NEO_USD",
    "rawPair": "NEO-USD-SWAP",
    "fundingRate": -0.00063327,
    "fundingTime": 1600876800000,
    "fundingTimeStr": "2020-09-23T16:00:00.000Z"
  },
  {
    "exchange": "OKEx",
    "pair": "NEO_USD",
    "rawPair": "NEO-USD-SWAP",
    "fundingRate": -0.003,
    "fundingTime": 1600905600000,
    "fundingTimeStr": "2020-09-24T00:00:00.000Z"
  },
  {
    "exchange": "OKEx",
    "pair": "NEO_USD",
    "rawPair": "NEO-USD-SWAP",
    "fundingRate": -0.00074341,
    "fundingTime": 1600934400000,
    "fundingTimeStr": "2020-09-24T08:00:00.000Z"
  }
]
