[
  {
    "exchange": "OKEx",
    "pair": "RVN_USDT",
    "rawPair": "RVN-USDT-SWAP",
    "fundingRate": 0,
    "fundingTime": 1619164800000,
    "fundingTimeStr": "2021-04-23T08:00:00.000Z"
  },
  {
    "exchange": "OKEx",
    "pair": "RVN_USDT",
    "rawPair": "RVN-USDT-SWAP",
    "fundingRate": 0.0003,
    "fundingTime": 1619193600000,
    "fundingTimeStr": "2021-04-23T16:00:00.000Z"
  },
  {
    "exchange": "OKEx",
    "pair": "RVN_USDT",
    "rawPair": "RVN-USDT-SWAP",
    "fundingRate": 0.00004201,
    "fundingTime": 1619222400000,
    "fundingTimeStr": "2021-04-24T00:00:00.000Z"
  },
  {
    "exchange": "OKEx",
    "pair": "RVN_USDT",
    "rawPair": "RVN-USDT-SWAP",
    "fundingRate": 0.00039116,
    "fundingTime": 1619251200000,
    "fundingTimeStr": "2021-04-24T08:00:00.000Z"
  },
  {
    "exchange": "OKEx",
    "pair": "RVN_USDT",
    "rawPair": "RVN-USDT-SWAP",
    "fundingRate": -0.00011582,
    "fundingTime": 1619280000000,
    "fundingTimeStr": "2021-04-24T16:00:00.000Z"
  },
  {
    "exchange": "OKEx",
    "pair": "RVN_USDT",
    "rawPair": "RVN-USDT-SWAP",
    "fundingRate": 0.00046298,
    "fundingTime": 1619308800000,
    "fundingTimeStr": "2021-04-25T00:00:00.000Z"
  },
  {
    "exchange": "OKEx",
    "pair": "RVN_USDT",
    "rawPair": "RVN-USDT-SWAP",
    "fundingRate": 0.00006868,
    "fundingTime": 1619337600000,
    "fundingTimeStr": "2021-04-25T08:00:00.000Z"
  },
  {
    "exchange": "OKEx",
    "pair": "RVN_USDT",
    "rawPair": "RVN-USDT-SWAP",
    "fundingRate": 0.00054342,
    "fundingTime": 1619366400000,
    "fundingTimeStr": "2021-04-25T16:00:00.000Z"
  },
  {
    "exchange": "OKEx",
    "pair": "RVN_USDT",
    "rawPair": "RVN-USDT-SWAP",
    "fundingRate": 0.00024896,
    "fundingTime": 1619395200000,
    "fundingTimeStr": "2021-04-26T00:00:00.000Z"
  },
  {
    "exchange": "OKEx",
    "pair": "RVN_USDT",
    "rawPair": "RVN-USDT-SWAP",
    "fundingRate": 0.00046732,
    "fundingTime": 1619424000000,
    "fundingTimeStr": "2021-04-26T08:00:00.000Z"
  },
  {
    "exchange": "OKEx",
    "pair": "RVN_USDT",
    "rawPair": "RVN-USDT-SWAP",
    "fundingRate": -0.00033346,
    "fundingTime": 1619452800000,
    "fundingTimeStr": "2021-04-26T16:00:00.000Z"
  },
  {
    "exchange": "OKEx",
    "pair": "RVN_USDT",
    "rawPair": "RVN-USDT-SWAP",
    "fundingRate": 0.00127186,
    "fundingTime": 1619481600000,
    "fundingTimeStr": "2021-04-27T00:00:00.000Z"
  },
  {
    "exchange": "OKEx",
    "pair": "RVN_USDT",
    "rawPair": "RVN-USDT-SWAP",
    "fundingRate": 0.00021356,
    "fundingTime": 1619510400000,
    "fundingTimeStr": "2021-04-27T08:00:00.000Z"
  },
  {
    "exchange": "OKEx",
    "pair": "RVN_USDT",
    "rawPair": "RVN-USDT-SWAP",
    "fundingRate": 0.00099151,
    "fundingTime": 1619539200000,
    "fundingTimeStr": "2021-04-27T16:00:00.000Z"
  },
  {
    "exchange": "OKEx",
    "pair": "RVN_USDT",
    "rawPair": "RVN-USDT-SWAP",
    "fundingRate": 0.00030602,
    "fundingTime": 1619568000000,
    "fundingTimeStr": "2021-04-28T00:00:00.000Z"
  },
  {
    "exchange": "OKEx",
    "pair": "RVN_USDT",
    "rawPair": "RVN-USDT-SWAP",
    "fundingRate": 0.000912,
    "fundingTime": 1619596800000,
    "fundingTimeStr": "2021-04-28T08:00:00.000Z"
  },
  {
    "exchange": "OKEx",
    "pair": "RVN_USDT",
    "rawPair": "RVN-USDT-SWAP",
    "fundingRate": 0.00036753,
    "fundingTime": 1619625600000,
    "fundingTimeStr": "2021-04-28T16:00:00.000Z"
  },
  {
    "exchange": "OKEx",
    "pair": "RVN_USDT",
    "rawPair": "RVN-USDT-SWAP",
    "fundingRate": 0.00034488,
    "fundingTime": 1619654400000,
    "fundingTimeStr": "2021-04-29T00:00:00.000Z"
  },
  {
    "exchange": "OKEx",
    "pair": "RVN_USDT",
    "rawPair": "RVN-USDT-SWAP",
    "fundingRate": 0.00025341,
    "fundingTime": 1619683200000,
    "fundingTimeStr": "2021-04-29T08:00:00.000Z"
  },
  {
    "exchange": "OKEx",
    "pair": "RVN_USDT",
    "rawPair": "RVN-USDT-SWAP",
    "fundingRate": 0.00052739,
    "fundingTime": 1619712000000,
    "fundingTimeStr": "2021-04-29T16:00:00.000Z"
  },
  {
    "exchange": "OKEx",
    "pair": "RVN_USDT",
    "rawPair": "RVN-USDT-SWAP",
    "fundingRate": 0.00097333,
    "fundingTime": 1619740800000,
    "fundingTimeStr": "2021-04-30T00:00:00.000Z"
  },
  {
    "exchange": "OKEx",
    "pair": "RVN_USDT",
    "rawPair": "RVN-USDT-SWAP",
    "fundingRate": 0.00040062,
    "fundingTime": 1619769600000,
    "fundingTimeStr": "2021-04-30T08:00:00.000Z"
  },
  {
    "exchange": "OKEx",
    "pair": "RVN_USDT",
    "rawPair": "RVN-USDT-SWAP",
    "fundingRate": 0.00077731,
    "fundingTime": 1619798400000,
    "fundingTimeStr": "2021-04-30T16:00:00.000Z"
  },
  {
    "exchange": "OKEx",
    "pair": "RVN_USDT",
    "rawPair": "RVN-USDT-SWAP",
    "fundingRate": 0.00083317,
    "fundingTime": 1619827200000,
    "fundingTimeStr": "2021-05-01T00:00:00.000Z"
  },
  {
    "exchange": "OKEx",
    "pair": "RVN_USDT",
    "rawPair": "RVN-USDT-SWAP",
    "fundingRate": 0.00033251,
    "fundingTime": 1619856000000,
    "fundingTimeStr": "2021-05-01T08:00:00.000Z"
  },
  {
    "exchange": "OKEx",
    "pair": "RVN_USDT",
    "rawPair": "RVN-USDT-SWAP",
    "fundingRate": 0.00138076,
    "fundingTime": 1619884800000,
    "fundingTimeStr": "2021-05-01T16:00:00.000Z"
  },
  {
    "exchange": "OKEx",
    "pair": "RVN_USDT",
    "rawPair": "RVN-USDT-SWAP",
    "fundingRate": 0.00036358,
    "fundingTime": 1619913600000,
    "fundingTimeStr": "2021-05-02T00:00:00.000Z"
  },
  {
    "exchange": "OKEx",
    "pair": "RVN_USDT",
    "rawPair": "RVN-USDT-SWAP",
    "fundingRate": 0.00139734,
    "fundingTime": 1619942400000,
    "fundingTimeStr": "2021-05-02T08:00:00.000Z"
  },
  {
    "exchange": "OKEx",
    "pair": "RVN_USDT",
    "rawPair": "RVN-USDT-SWAP",
    "fundingRate": 0.0003647,
    "fundingTime": 1619971200000,
    "fundingTimeStr": "2021-05-02T16:00:00.000Z"
  },
  {
    "exchange": "OKEx",
    "pair": "RVN_USDT",
    "rawPair": "RVN-USDT-SWAP",
    "fundingRate": 0.00100287,
    "fundingTime": 1620000000000,
    "fundingTimeStr": "2021-05-03T00:00:00.000Z"
  },
  {
    "exchange": "OKEx",
    "pair": "RVN_USDT",
    "rawPair": "RVN-USDT-SWAP",
    "fundingRate": 0.00107267,
    "fundingTime": 1620028800000,
    "fundingTimeStr": "2021-05-03T08:00:00.000Z"
  },
  {
    "exchange": "OKEx",
    "pair": "RVN_USDT",
    "rawPair": "RVN-USDT-SWAP",
    "fundingRate": 0.00112619,
    "fundingTime": 1620057600000,
    "fundingTimeStr": "2021-05-03T16:00:00.000Z"
  },
  {
    "exchange": "OKEx",
    "pair": "RVN_USDT",
    "rawPair": "RVN-USDT-SWAP",
    "fundingRate": 0.00172338,
    "fundingTime": 1620086400000,
    "fundingTimeStr": "2021-05-04T00:00:00.000Z"
  },
  {
    "exchange": "OKEx",
    "pair": "RVN_USDT",
    "rawPair": "RVN-USDT-SWAP",
    "fundingRate": 0.0006004,
    "fundingTime": 1620115200000,
    "fundingTimeStr": "2021-05-04T08:00:00.000Z"
  },
  {
    "exchange": "OKEx",
    "pair": "RVN_USDT",
    "rawPair": "RVN-USDT-SWAP",
    "fundingRate": 0.00066343,
    "fundingTime": 1620144000000,
    "fundingTimeStr": "2021-05-04T16:00:00.000Z"
  },
  {
    "exchange": "OKEx",
    "pair": "RVN_USDT",
    "rawPair": "RVN-USDT-SWAP",
    "fundingRate": 0.00113046,
    "fundingTime": 1620172800000,
    "fundingTimeStr": "2021-05-05T00:00:00.000Z"
  },
  {
    "exchange": "OKEx",
    "pair": "RVN_USDT",
    "rawPair": "RVN-USDT-SWAP",
    "fundingRate": -0.00017674,
    "fundingTime": 1620201600000,
    "fundingTimeStr": "2021-05-05T08:00:00.000Z"
  },
  {
    "exchange": "OKEx",
    "pair": "RVN_USDT",
    "rawPair": "RVN-USDT-SWAP",
    "fundingRate": 0.00129733,
    "fundingTime": 1620230400000,
    "fundingTimeStr": "2021-05-05T16:00:00.000Z"
  },
  {
    "exchange": "OKEx",
    "pair": "RVN_USDT",
    "rawPair": "RVN-USDT-SWAP",
    "fundingRate": 0.0008323,
    "fundingTime": 1620259200000,
    "fundingTimeStr": "2021-05-06T00:00:00.000Z"
  },
  {
    "exchange": "OKEx",
    "pair": "RVN_USDT",
    "rawPair": "RVN-USDT-SWAP",
    "fundingRate": 0.00082615,
    "fundingTime": 1620288000000,
    "fundingTimeStr": "2021-05-06T08:00:00.000Z"
  },
  {
    "exchange": "OKEx",
    "pair": "RVN_USDT",
    "rawPair": "RVN-USDT-SWAP",
    "fundingRate": 0.00154415,
    "fundingTime": 1620316800000,
    "fundingTimeStr": "2021-05-06T16:00:00.000Z"
  },
  {
    "exchange": "OKEx",
    "pair": "RVN_USDT",
    "rawPair": "RVN-USDT-SWAP",
    "fundingRate": 0.00144952,
    "fundingTime": 1620345600000,
    "fundingTimeStr": "2021-05-07T00:00:00.000Z"
  },
  {
    "exchange": "OKEx",
    "pair": "RVN_USDT",
    "rawPair": "RVN-USDT-SWAP",
    "fundingRate": 0.00115136,
    "fundingTime": 1620374400000,
    "fundingTimeStr": "2021-05-07T08:00:00.000Z"
  },
  {
    "exchange": "OKEx",
    "pair": "RVN_USDT",
    "rawPair": "RVN-USDT-SWAP",
    "fundingRate": 0.00077748,
    "fundingTime": 1620403200000,
    "fundingTimeStr": "2021-05-07T16:00:00.000Z"
  },
  {
    "exchange": "OKEx",
    "pair": "RVN_USDT",
    "rawPair": "RVN-USDT-SWAP",
    "fundingRate": 0.001359,
    "fundingTime": 1620432000000,
    "fundingTimeStr": "2021-05-08T00:00:00.000Z"
  },
  {
    "exchange": "OKEx",
    "pair": "RVN_USDT",
    "rawPair": "RVN-USDT-SWAP",
    "fundingRate": 0.00050056,
    "fundingTime": 1620460800000,
    "fundingTimeStr": "2021-05-08T08:00:00.000Z"
  },
  {
    "exchange": "OKEx",
    "pair": "RVN_USDT",
    "rawPair": "RVN-USDT-SWAP",
    "fundingRate": 0.0012801,
    "fundingTime": 1620489600000,
    "fundingTimeStr": "2021-05-08T16:00:00.000Z"
  },
  {
    "exchange": "OKEx",
    "pair": "RVN_USDT",
    "rawPair": "RVN-USDT-SWAP",
    "fundingRate": 0.0010343,
    "fundingTime": 1620518400000,
    "fundingTimeStr": "2021-05-09T00:00:00.000Z"
  },
  {
    "exchange": "OKEx",
    "pair": "RVN_USDT",
    "rawPair": "RVN-USDT-SWAP",
    "fundingRate": 0.00125031,
    "fundingTime": 1620547200000,
    "fundingTimeStr": "2021-05-09T08:00:00.000Z"
  },
  {
    "exchange": "OKEx",
    "pair": "RVN_USDT",
    "rawPair": "RVN-USDT-SWAP",
    "fundingRate": 0.00028503,
    "fundingTime": 1620576000000,
    "fundingTimeStr": "2021-05-09T16:00:00.000Z"
  },
  {
    "exchange": "OKEx",
    "pair": "RVN_USDT",
    "rawPair": "RVN-USDT-SWAP",
    "fundingRate": 0.00133166,
    "fundingTime": 1620604800000,
    "fundingTimeStr": "2021-05-10T00:00:00.000Z"
  },
  {
    "exchange": "OKEx",
    "pair": "RVN_USDT",
    "rawPair": "RVN-USDT-SWAP",
    "fundingRate": 0.000253,
    "fundingTime": 1620633600000,
    "fundingTimeStr": "2021-05-10T08:00:00.000Z"
  },
  {
    "exchange": "OKEx",
    "pair": "RVN_USDT",
    "rawPair": "RVN-USDT-SWAP",
    "fundingRate": 0.00147397,
    "fundingTime": 1620662400000,
    "fundingTimeStr": "2021-05-10T16:00:00.000Z"
  },
  {
    "exchange": "OKEx",
    "pair": "RVN_USDT",
    "rawPair": "RVN-USDT-SWAP",
    "fundingRate": 0.00006827,
    "fundingTime": 1620691200000,
    "fundingTimeStr": "2021-05-11T00:00:00.000Z"
  },
  {
    "exchange": "OKEx",
    "pair": "RVN_USDT",
    "rawPair": "RVN-USDT-SWAP",
    "fundingRate": 0.0000353,
    "fundingTime": 1620720000000,
    "fundingTimeStr": "2021-05-11T08:00:00.000Z"
  },
  {
    "exchange": "OKEx",
    "pair": "RVN_USDT",
    "rawPair": "RVN-USDT-SWAP",
    "fundingRate": 0.00024829,
    "fundingTime": 1620748800000,
    "fundingTimeStr": "2021-05-11T16:00:00.000Z"
  },
  {
    "exchange": "OKEx",
    "pair": "RVN_USDT",
    "rawPair": "RVN-USDT-SWAP",
    "fundingRate": 0.0002345,
    "fundingTime": 1620777600000,
    "fundingTimeStr": "2021-05-12T00:00:00.000Z"
  },
  {
    "exchange": "OKEx",
    "pair": "RVN_USDT",
    "rawPair": "RVN-USDT-SWAP",
    "fundingRate": 0.0007063,
    "fundingTime": 1620806400000,
    "fundingTimeStr": "2021-05-12T08:00:00.000Z"
  },
  {
    "exchange": "OKEx",
    "pair": "RVN_USDT",
    "rawPair": "RVN-USDT-SWAP",
    "fundingRate": 0.00051491,
    "fundingTime": 1620835200000,
    "fundingTimeStr": "2021-05-12T16:00:00.000Z"
  },
  {
    "exchange": "OKEx",
    "pair": "RVN_USDT",
    "rawPair": "RVN-USDT-SWAP",
    "fundingRate": 0.00030037,
    "fundingTime": 1620864000000,
    "fundingTimeStr": "2021-05-13T00:00:00.000Z"
  },
  {
    "exchange": "OKEx",
    "pair": "RVN_USDT",
    "rawPair": "RVN-USDT-SWAP",
    "fundingRate": 0.00051931,
    "fundingTime": 1620892800000,
    "fundingTimeStr": "2021-05-13T08:00:00.000Z"
  },
  {
    "exchange": "OKEx",
    "pair": "RVN_USDT",
    "rawPair": "RVN-USDT-SWAP",
    "fundingRate": 0.00023237,
    "fundingTime": 1620921600000,
    "fundingTimeStr": "2021-05-13T16:00:00.000Z"
  },
  {
    "exchange": "OKEx",
    "pair": "RVN_USDT",
    "rawPair": "RVN-USDT-SWAP",
    "fundingRate": 0.00035966,
    "fundingTime": 1620950400000,
    "fundingTimeStr": "2021-05-14T00:00:00.000Z"
  },
  {
    "exchange": "OKEx",
    "pair": "RVN_USDT",
    "rawPair": "RVN-USDT-SWAP",
    "fundingRate": 0.00026534,
    "fundingTime": 1620979200000,
    "fundingTimeStr": "2021-05-14T08:00:00.000Z"
  },
  {
    "exchange": "OKEx",
    "pair": "RVN_USDT",
    "rawPair": "RVN-USDT-SWAP",
    "fundingRate": 0.00034355,
    "fundingTime": 1621008000000,
    "fundingTimeStr": "2021-05-14T16:00:00.000Z"
  },
  {
    "exchange": "OKEx",
    "pair": "RVN_USDT",
    "rawPair": "RVN-USDT-SWAP",
    "fundingRate": 0.00046685,
    "fundingTime": 1621036800000,
    "fundingTimeStr": "2021-05-15T00:00:00.000Z"
  },
  {
    "exchange": "OKEx",
    "pair": "RVN_USDT",
    "rawPair": "RVN-USDT-SWAP",
    "fundingRate": 0.00038352,
    "fundingTime": 1621065600000,
    "fundingTimeStr": "2021-05-15T08:00:00.000Z"
  },
  {
    "exchange": "OKEx",
    "pair": "RVN_USDT",
    "rawPair": "RVN-USDT-SWAP",
    "fundingRate": 0.00048047,
    "fundingTime": 1621094400000,
    "fundingTimeStr": "2021-05-15T16:00:00.000Z"
  }
]
